{
  "_generated": "Generated by SweetTooth, do not edit",
  "description": "Makes any non-active window semi-transparent",
  "extension-id": "transparent-inactive-windows",
  "gettext-domain": "gnome-shell-extensions",
  "name": "Transparent Inactive Windows",
  "settings-schema": "org.gnome.shell.extensions.transparent-inactive-windows",
  "shell-version": [
    "45",
    "46",
    "47",
    "48"
  ],
  "url": "https://github.com/elro/semi-transparent-inactive-windows",
  "uuid": "semi-transparent-inactive-windows@elro.github.com",
  "version": 1
} 